{
    "user.status.1": "Not Confirmed",
    "user.status.10": "Confirmed",
    "user.status.20": "ETH Wallet Confirmed",
    "user.status.30": "Contributer",
    "user.status.40": "KYC Required",
    "user.status.45": "Crypto Wallet Required",
    "user.status.50": "Verified Account",
    "user.status.60": "Funds Returned",
    "user.status.70": "Black List",
    "user.status.80": "No Response No Wallet",
    "user.kyc_status.10": "Partial Docs",
    "user.kyc_status.20": "ID Missing/Invalid",
    "user.kyc_status.30": "UB Missing/Invalid",
    "user.kyc_status.40": "Verified",
    "user.marketer.0": "No",
    "user.marketer.1": "Yes",
    "country_iso.AX": "Aland Islands",
    "country_iso.AF": "Afghanistan",
    "country_iso.AL": "Albania",
    "country_iso.DZ": "Algeria",
    "country_iso.AS": "American Samoa",
    "country_iso.AD": "Andorra",
    "country_iso.AO": "Angola",
    "country_iso.AI": "Anguilla",
    "country_iso.AQ": "Antarctica",
    "country_iso.AG": "Antigua and Barbuda",
    "country_iso.AR": "Argentina",
    "country_iso.AM": "Armenia",
    "country_iso.AW": "Aruba",
    "country_iso.AU": "Australia",
    "country_iso.AT": "Austria",
    "country_iso.AZ": "Azerbaijan",
    "country_iso.BS": "Bahamas",
    "country_iso.BH": "Bahrain",
    "country_iso.BD": "Bangladesh",
    "country_iso.BB": "Barbados",
    "country_iso.BY": "Belarus",
    "country_iso.BE": "Belgium",
    "country_iso.BZ": "Belize",
    "country_iso.BJ": "Benin",
    "country_iso.BM": "Bermuda",
    "country_iso.BT": "Bhutan",
    "country_iso.BO": "Bolivia",
    "country_iso.BA": "Bosnia and Herzegovina",
    "country_iso.BW": "Botswana",
    "country_iso.BV": "Bouvet Island",
    "country_iso.BR": "Brazil",
    "country_iso.VG": "British Virgin Islands",
    "country_iso.IO": "British Indian Ocean Territory",
    "country_iso.BN": "Brunei Darussalam",
    "country_iso.BG": "Bulgaria",
    "country_iso.BF": "Burkina Faso",
    "country_iso.BI": "Burundi",
    "country_iso.KH": "Cambodia",
    "country_iso.CM": "Cameroon",
    "country_iso.CA": "Canada",
    "country_iso.CV": "Cape Verde",
    "country_iso.KY": "Cayman Islands",
    "country_iso.CF": "Central African Republic",
    "country_iso.TD": "Chad",
    "country_iso.CL": "Chile",
    "country_iso.CN": "China",
    "country_iso.HK": "Hong Kong SAR China",
    "country_iso.MO": "Macao SAR China",
    "country_iso.CX": "Christmas Island",
    "country_iso.CC": "Cocos (Keeling) Islands",
    "country_iso.CO": "Colombia",
    "country_iso.KM": "Comoros",
    "country_iso.CG": "Congo (Brazzaville)",
    "country_iso.CD": "Congo (Kinshasa)",
    "country_iso.CK": "Cook Islands",
    "country_iso.CR": "Costa Rica",
    "country_iso.CI": "Côte d'Ivoire",
    "country_iso.HR": "Croatia",
    "country_iso.CU": "Cuba",
    "country_iso.CY": "Cyprus",
    "country_iso.CZ": "Czech Republic",
    "country_iso.DK": "Denmark",
    "country_iso.DJ": "Djibouti",
    "country_iso.DM": "Dominica",
    "country_iso.DO": "Dominican Republic",
    "country_iso.EC": "Ecuador",
    "country_iso.EG": "Egypt",
    "country_iso.SV": "El Salvador",
    "country_iso.GQ": "Equatorial Guinea",
    "country_iso.ER": "Eritrea",
    "country_iso.EE": "Estonia",
    "country_iso.ET": "Ethiopia",
    "country_iso.FK": "Falkland Islands (Malvinas)",
    "country_iso.FO": "Faroe Islands",
    "country_iso.FJ": "Fiji",
    "country_iso.FI": "Finland",
    "country_iso.FR": "France",
    "country_iso.GF": "French Guiana",
    "country_iso.PF": "French Polynesia",
    "country_iso.TF": "French Southern Territories",
    "country_iso.GA": "Gabon",
    "country_iso.GM": "Gambia",
    "country_iso.GE": "Georgia",
    "country_iso.DE": "Germany",
    "country_iso.GH": "Ghana",
    "country_iso.GI": "Gibraltar",
    "country_iso.GR": "Greece",
    "country_iso.GL": "Greenland",
    "country_iso.GD": "Grenada",
    "country_iso.GP": "Guadeloupe",
    "country_iso.GU": "Guam",
    "country_iso.GT": "Guatemala",
    "country_iso.GG": "Guernsey",
    "country_iso.GN": "Guinea",
    "country_iso.GW": "Guinea-Bissau",
    "country_iso.GY": "Guyana",
    "country_iso.HT": "Haiti",
    "country_iso.HM": "Heard and Mcdonald Islands",
    "country_iso.VA": "Holy See (Vatican City State)",
    "country_iso.HN": "Honduras",
    "country_iso.HU": "Hungary",
    "country_iso.IS": "Iceland",
    "country_iso.IN": "India",
    "country_iso.ID": "Indonesia",
    "country_iso.IR": "Iran Islamic Republic of",
    "country_iso.IQ": "Iraq",
    "country_iso.IE": "Ireland",
    "country_iso.IM": "Isle of Man",
    "country_iso.IL": "Israel",
    "country_iso.IT": "Italy",
    "country_iso.JM": "Jamaica",
    "country_iso.JP": "Japan",
    "country_iso.JE": "Jersey",
    "country_iso.JO": "Jordan",
    "country_iso.KZ": "Kazakhstan",
    "country_iso.KE": "Kenya",
    "country_iso.KI": "Kiribati",
    "country_iso.KP": "Korea (North)",
    "country_iso.KR": "Korea (South)",
    "country_iso.KW": "Kuwait",
    "country_iso.KG": "Kyrgyzstan",
    "country_iso.LA": "Lao PDR",
    "country_iso.LV": "Latvia",
    "country_iso.LB": "Lebanon",
    "country_iso.LS": "Lesotho",
    "country_iso.LR": "Liberia",
    "country_iso.LY": "Libya",
    "country_iso.LI": "Liechtenstein",
    "country_iso.LT": "Lithuania",
    "country_iso.LU": "Luxembourg",
    "country_iso.MK": "Macedonia Republic of",
    "country_iso.MG": "Madagascar",
    "country_iso.MW": "Malawi",
    "country_iso.MY": "Malaysia",
    "country_iso.MV": "Maldives",
    "country_iso.ML": "Mali",
    "country_iso.MT": "Malta",
    "country_iso.MH": "Marshall Islands",
    "country_iso.MQ": "Martinique",
    "country_iso.MR": "Mauritania",
    "country_iso.MU": "Mauritius",
    "country_iso.YT": "Mayotte",
    "country_iso.MX": "Mexico",
    "country_iso.FM": "Micronesia Federated States of",
    "country_iso.MD": "Moldova",
    "country_iso.MC": "Monaco",
    "country_iso.MN": "Mongolia",
    "country_iso.ME": "Montenegro",
    "country_iso.MS": "Montserrat",
    "country_iso.MA": "Morocco",
    "country_iso.MZ": "Mozambique",
    "country_iso.MM": "Myanmar",
    "country_iso.NA": "Namibia",
    "country_iso.NR": "Nauru",
    "country_iso.NP": "Nepal",
    "country_iso.NL": "Netherlands",
    "country_iso.AN": "Netherlands Antilles",
    "country_iso.NC": "New Caledonia",
    "country_iso.NZ": "New Zealand",
    "country_iso.NI": "Nicaragua",
    "country_iso.NE": "Niger",
    "country_iso.NG": "Nigeria",
    "country_iso.NU": "Niue",
    "country_iso.NF": "Norfolk Island",
    "country_iso.MP": "Northern Mariana Islands",
    "country_iso.NO": "Norway",
    "country_iso.OM": "Oman",
    "country_iso.PK": "Pakistan",
    "country_iso.PW": "Palau",
    "country_iso.PS": "Palestinian Territory",
    "country_iso.PA": "Panama",
    "country_iso.PG": "Papua New Guinea",
    "country_iso.PY": "Paraguay",
    "country_iso.PE": "Peru",
    "country_iso.PH": "Philippines",
    "country_iso.PN": "Pitcairn",
    "country_iso.PL": "Poland",
    "country_iso.PT": "Portugal",
    "country_iso.PR": "Puerto Rico",
    "country_iso.QA": "Qatar",
    "country_iso.RE": "Réunion",
    "country_iso.RO": "Romania",
    "country_iso.RU": "Russian Federation",
    "country_iso.RW": "Rwanda",
    "country_iso.BL": "Saint-Barthélemy",
    "country_iso.SH": "Saint Helena",
    "country_iso.KN": "Saint Kitts and Nevis",
    "country_iso.LC": "Saint Lucia",
    "country_iso.MF": "Saint-Martin (French part)",
    "country_iso.PM": "Saint Pierre and Miquelon",
    "country_iso.VC": "Saint Vincent and Grenadines",
    "country_iso.WS": "Samoa",
    "country_iso.SM": "San Marino",
    "country_iso.ST": "Sao Tome and Principe",
    "country_iso.SA": "Saudi Arabia",
    "country_iso.SN": "Senegal",
    "country_iso.RS": "Serbia",
    "country_iso.SC": "Seychelles",
    "country_iso.SL": "Sierra Leone",
    "country_iso.SG": "Singapore",
    "country_iso.SK": "Slovakia",
    "country_iso.SI": "Slovenia",
    "country_iso.SB": "Solomon Islands",
    "country_iso.SO": "Somalia",
    "country_iso.ZA": "South Africa",
    "country_iso.GS": "South Georgia and the South Sandwich Islands",
    "country_iso.SS": "South Sudan",
    "country_iso.ES": "Spain",
    "country_iso.LK": "Sri Lanka",
    "country_iso.SD": "Sudan",
    "country_iso.SR": "Suriname",
    "country_iso.SJ": "Svalbard and Jan Mayen Islands",
    "country_iso.SZ": "Swaziland",
    "country_iso.SE": "Sweden",
    "country_iso.CH": "Switzerland",
    "country_iso.SY": "Syrian Arab Republic (Syria)",
    "country_iso.TW": "Taiwan Republic of China",
    "country_iso.TJ": "Tajikistan",
    "country_iso.TZ": "Tanzania United Republic of",
    "country_iso.TH": "Thailand",
    "country_iso.TL": "Timor-Leste",
    "country_iso.TG": "Togo",
    "country_iso.TK": "Tokelau",
    "country_iso.TO": "Tonga",
    "country_iso.TT": "Trinidad and Tobago",
    "country_iso.TN": "Tunisia",
    "country_iso.TR": "Turkey",
    "country_iso.TM": "Turkmenistan",
    "country_iso.TC": "Turks and Caicos Islands",
    "country_iso.TV": "Tuvalu",
    "country_iso.UG": "Uganda",
    "country_iso.UA": "Ukraine",
    "country_iso.AE": "United Arab Emirates",
    "country_iso.GB": "United Kingdom",
    "country_iso.US": "United States of America",
    "country_iso.UM": "US Minor Outlying Islands",
    "country_iso.UY": "Uruguay",
    "country_iso.UZ": "Uzbekistan",
    "country_iso.VU": "Vanuatu",
    "country_iso.VE": "Venezuela (Bolivarian Republic)",
    "country_iso.VN": "Viet Nam",
    "country_iso.VI": "Virgin Islands US",
    "country_iso.WF": "Wallis and Futuna Islands",
    "country_iso.EH": "Western Sahara",
    "country_iso.YE": "Yemen",
    "country_iso.ZM": "Zambia",
    "country_iso.ZW": "Zimbabwe",
    "transaction.status.1": "Waiting Approval",
    "transaction.status.10": "Approved",
    "transaction.status.20": "Declined",
    "transaction.status.30": "KYC Required",
    "transaction.status.40": "Funds Returned",
    "transaction.status.50": "Crypto wallet required",
    "transaction.currency.ether": "ETH",
    "transaction.currency.BTC": "BTC",
    "transaction.currency.BCH": "BCH",
    "transaction.payment_type.1": "Wire",
    "transaction.payment_type.10": "Crypto",
    "transaction.type.1": "Deposit",
    "transaction.type.10": "Return Funds",
    "token.status.1": "Not Sent",
    "token.status.10": "Created",
    "token.status.20": "Pending",
    "token.status.30": "Confirmed",
    "token.status.40": "Failed",
    "token.status.50": "Manual"
}
